cratedb_toolkit/__init__.py
cratedb_toolkit/cli.py
cratedb_toolkit/config.py
cratedb_toolkit/exception.py
cratedb_toolkit/model.py
cratedb_toolkit/option.py
cratedb_toolkit/adapter/__init__.py
cratedb_toolkit/adapter/pymongo/__init__.py
cratedb_toolkit/adapter/pymongo/api.py
cratedb_toolkit/adapter/pymongo/collection.py
cratedb_toolkit/adapter/pymongo/cursor.py
cratedb_toolkit/adapter/pymongo/reactor.py
cratedb_toolkit/adapter/pymongo/util.py
cratedb_toolkit/adapter/rockset/__init__.py
cratedb_toolkit/adapter/rockset/cli.py
cratedb_toolkit/adapter/rockset/server/__init__.py
cratedb_toolkit/adapter/rockset/server/dependencies.py
cratedb_toolkit/adapter/rockset/server/main.py
cratedb_toolkit/adapter/rockset/server/api/__init__.py
cratedb_toolkit/adapter/rockset/server/api/collection.py
cratedb_toolkit/adapter/rockset/server/api/document.py
cratedb_toolkit/adapter/rockset/server/api/query.py
cratedb_toolkit/cfr/__init__.py
cratedb_toolkit/cfr/cli.py
cratedb_toolkit/cfr/info.py
cratedb_toolkit/cfr/jobstats.py
cratedb_toolkit/cfr/marimo.py
cratedb_toolkit/cfr/systable.py
cratedb_toolkit/cluster/__init__.py
cratedb_toolkit/cluster/cli.py
cratedb_toolkit/cluster/core.py
cratedb_toolkit/cluster/croud.py
cratedb_toolkit/cluster/guide.py
cratedb_toolkit/cluster/model.py
cratedb_toolkit/cmd/__init__.py
cratedb_toolkit/cmd/tail/__init__.py
cratedb_toolkit/cmd/tail/cli.py
cratedb_toolkit/cmd/tail/main.py
cratedb_toolkit/datasets/__init__.py
cratedb_toolkit/datasets/core.py
cratedb_toolkit/datasets/kaggle.py
cratedb_toolkit/datasets/model.py
cratedb_toolkit/datasets/store.py
cratedb_toolkit/datasets/tutorial.py
cratedb_toolkit/datasets/util.py
cratedb_toolkit/dms/__init__.py
cratedb_toolkit/dms/cli.py
cratedb_toolkit/dms/table_mapping.py
cratedb_toolkit/docs/__init__.py
cratedb_toolkit/docs/cli.py
cratedb_toolkit/docs/functions.py
cratedb_toolkit/docs/model.py
cratedb_toolkit/docs/settings.py
cratedb_toolkit/docs/util.py
cratedb_toolkit/iac/__init__.py
cratedb_toolkit/iac/aws.py
cratedb_toolkit-0.0.41.dist-info/licenses/LICENSE
cratedb_toolkit-0.0.41.dist-info/METADATA
cratedb_toolkit-0.0.41.dist-info/WHEEL
cratedb_toolkit-0.0.41.dist-info/entry_points.txt
cratedb_toolkit-0.0.41.dist-info/top_level.txt
cratedb_toolkit-0.0.41.dist-info/RECORD
