Metadata-Version: 2.4
Name: cratedb-toolkit
Version: 0.0.41
Summary: CrateDB Toolkit
Author: The CrateDB Developers
Maintainer-email: Andreas Motl <andreas.motl@crate.io>, Hernan Cianfagna <hernan@crate.io>, Niklas Schmidtmer <niklas@crate.io>, Walter Behmann <walter@crate.io>
License: AGPL 3, EUPL 1.2
Project-URL: Changelog, https://github.com/crate/cratedb-toolkit/blob/main/CHANGES.md
Project-URL: Documentation, https://cratedb-toolkit.readthedocs.io/
Project-URL: Homepage, https://cratedb-toolkit.readthedocs.io/
Project-URL: Issues, https://github.com/crate/cratedb-toolkit/issues
Project-URL: Repository, https://github.com/crate/cratedb-toolkit
Keywords: cratedb,cratedb-admin,cratedb-cloud,cratedb-diagnostics,cratedb-shell,data-processing,data-retention,managed-cratedb,toolkit
Classifier: Development Status :: 4 - Beta
Classifier: Environment :: Console
Classifier: Intended Audience :: Customer Service
Classifier: Intended Audience :: Developers
Classifier: Intended Audience :: Education
Classifier: Intended Audience :: End Users/Desktop
Classifier: Intended Audience :: Information Technology
Classifier: Intended Audience :: Manufacturing
Classifier: Intended Audience :: Science/Research
Classifier: Intended Audience :: System Administrators
Classifier: Intended Audience :: Telecommunications Industry
Classifier: License :: OSI Approved :: European Union Public Licence 1.2 (EUPL 1.2)
Classifier: License :: OSI Approved :: GNU Affero General Public License v3
Classifier: Operating System :: MacOS :: MacOS X
Classifier: Operating System :: Microsoft :: Windows
Classifier: Operating System :: POSIX :: Linux
Classifier: Operating System :: Unix
Classifier: Programming Language :: Python
Classifier: Programming Language :: Python :: 3 :: Only
Classifier: Programming Language :: Python :: 3.8
Classifier: Programming Language :: Python :: 3.9
Classifier: Programming Language :: Python :: 3.10
Classifier: Programming Language :: Python :: 3.11
Classifier: Programming Language :: Python :: 3.12
Classifier: Programming Language :: Python :: 3.13
Classifier: Topic :: Adaptive Technologies
Classifier: Topic :: Communications
Classifier: Topic :: Database
Classifier: Topic :: Documentation
Classifier: Topic :: Education
Classifier: Topic :: Internet
Classifier: Topic :: Internet :: WWW/HTTP
Classifier: Topic :: Office/Business
Classifier: Topic :: Scientific/Engineering
Classifier: Topic :: Software Development :: Embedded Systems
Classifier: Topic :: Software Development :: Libraries
Classifier: Topic :: Software Development :: Object Brokering
Classifier: Topic :: Software Development :: Pre-processors
Classifier: Topic :: Software Development :: Quality Assurance
Classifier: Topic :: Software Development :: Testing
Classifier: Topic :: Software Development :: Version Control
Classifier: Topic :: System :: Archiving
Classifier: Topic :: System :: Benchmark
Classifier: Topic :: System :: Clustering
Classifier: Topic :: System :: Distributed Computing
Classifier: Topic :: System :: Hardware
Classifier: Topic :: System :: Logging
Classifier: Topic :: System :: Monitoring
Classifier: Topic :: System :: Networking
Classifier: Topic :: System :: Systems Administration
Classifier: Topic :: Text Processing
Classifier: Topic :: Utilities
Requires-Python: >=3.8
License-File: LICENSE
Requires-Dist: attrs<26
Requires-Dist: boltons<26
Requires-Dist: cattrs<26
Requires-Dist: click<8.2
Requires-Dist: click-aliases<2,>=1.0.4
Requires-Dist: colorama<1
Requires-Dist: colorlog
Requires-Dist: crash
Requires-Dist: cratedb-sqlparse==0.0.15
Requires-Dist: croud<1.15,>=1.13
Requires-Dist: importlib-metadata; python_version < "3.8"
Requires-Dist: importlib-resources; python_version < "3.9"
Requires-Dist: keyrings-cryptfile<2
Requires-Dist: orjsonl<2
Requires-Dist: pympler<1.2
Requires-Dist: python-dateutil<3
Requires-Dist: python-dotenv<2
Requires-Dist: python-slugify<9
Requires-Dist: pyyaml<7
Requires-Dist: requests<3,>=2.28
Requires-Dist: sqlalchemy-cratedb>=0.41.0
Requires-Dist: sqlparse<0.6
Requires-Dist: tqdm<5
Requires-Dist: typing-extensions<5; python_version <= "3.7"
Requires-Dist: vasuki==0.7.0
Requires-Dist: verlib2<0.4
Requires-Dist: yarl<1.21
Provides-Extra: all
Requires-Dist: cratedb-toolkit[full,influxdb,mongodb]; extra == "all"
Provides-Extra: cfr
Requires-Dist: duckdb<1.4; extra == "cfr"
Requires-Dist: marimo<0.15; extra == "cfr"
Requires-Dist: matplotlib<3.11; extra == "cfr"
Requires-Dist: numpy<2.3; extra == "cfr"
Requires-Dist: pandas<2.3; extra == "cfr"
Requires-Dist: polars<1.33; extra == "cfr"
Requires-Dist: pyarrow<21.1; extra == "cfr"
Requires-Dist: queryanonymizer<1.2; extra == "cfr"
Provides-Extra: datasets
Requires-Dist: datasets<5; extra == "datasets"
Requires-Dist: kaggle<1.8; extra == "datasets"
Provides-Extra: develop
Requires-Dist: black[jupyter]<26; extra == "develop"
Requires-Dist: mypy<1.18; extra == "develop"
Requires-Dist: poethepoet<1; extra == "develop"
Requires-Dist: pyproject-fmt<3; extra == "develop"
Requires-Dist: ruff<0.13; extra == "develop"
Requires-Dist: validate-pyproject<1; extra == "develop"
Provides-Extra: docs
Requires-Dist: furo; extra == "docs"
Requires-Dist: myst-parser[linkify]<5,>=0.18; extra == "docs"
Requires-Dist: sphinx-autobuild==2021.3.14; extra == "docs"
Requires-Dist: sphinx-copybutton; extra == "docs"
Requires-Dist: sphinx-design-elements<1; extra == "docs"
Requires-Dist: sphinxcontrib-mermaid<2; extra == "docs"
Requires-Dist: sphinxext-opengraph<1; extra == "docs"
Provides-Extra: docs-api
Requires-Dist: beautifulsoup4; extra == "docs-api"
Requires-Dist: rich<15,>=3.3.2; extra == "docs-api"
Provides-Extra: dynamodb
Requires-Dist: boto3; extra == "dynamodb"
Requires-Dist: commons-codec>=0.0.20; extra == "dynamodb"
Requires-Dist: cratedb-toolkit[io-recipe]; extra == "dynamodb"
Provides-Extra: full
Requires-Dist: cratedb-toolkit[cfr,datasets,docs-api,io,mcp,service]; extra == "full"
Provides-Extra: influxdb
Requires-Dist: cratedb-toolkit[io]; extra == "influxdb"
Requires-Dist: influxio<1,>=0.6; extra == "influxdb"
Provides-Extra: io
Requires-Dist: cratedb-toolkit[io-base]; extra == "io"
Requires-Dist: sqlalchemy>=2; extra == "io"
Provides-Extra: io-base
Requires-Dist: cr8; extra == "io-base"
Requires-Dist: dask[dataframe]>=2020; extra == "io-base"
Requires-Dist: fsspec[http,s3]; extra == "io-base"
Requires-Dist: pandas<2.3,>=1; extra == "io-base"
Requires-Dist: polars<1.33; extra == "io-base"
Requires-Dist: universal-pathlib<0.3; extra == "io-base"
Provides-Extra: io-ingestr
Requires-Dist: cratedb-toolkit[io-base]; extra == "io-ingestr"
Requires-Dist: dlt<1.16,>=1.10; extra == "io-ingestr"
Requires-Dist: dlt-cratedb>=0.0.1; extra == "io-ingestr"
Requires-Dist: ingestr<0.14,>=0.13.61; extra == "io-ingestr"
Requires-Dist: sqlalchemy<2,>=1; extra == "io-ingestr"
Provides-Extra: io-recipe
Requires-Dist: tikray<0.3,>=0.2; extra == "io-recipe"
Provides-Extra: kinesis
Requires-Dist: aiobotocore<2.25; extra == "kinesis"
Requires-Dist: async-kinesis<3,>=2; extra == "kinesis"
Requires-Dist: botocore<1.41; extra == "kinesis"
Requires-Dist: commons-codec>=0.0.24; extra == "kinesis"
Requires-Dist: cratedb-toolkit[io-recipe]; extra == "kinesis"
Requires-Dist: lorrystream[carabas]>=0.0.6; extra == "kinesis"
Provides-Extra: mcp
Requires-Dist: mcp<1.5; python_version >= "3.10" and extra == "mcp"
Provides-Extra: mongodb
Requires-Dist: commons-codec[mongodb]>=0.0.22; extra == "mongodb"
Requires-Dist: cratedb-toolkit[io,io-recipe]; extra == "mongodb"
Requires-Dist: orjson<4,>=3.3.1; extra == "mongodb"
Requires-Dist: pymongo<4.10,>=3.10.1; extra == "mongodb"
Requires-Dist: python-bsonjs<0.8; extra == "mongodb"
Requires-Dist: rich<15,>=3.3.2; extra == "mongodb"
Requires-Dist: undatum<1.1; extra == "mongodb"
Provides-Extra: pymongo
Requires-Dist: jessiql==1.0.0rc1; extra == "pymongo"
Requires-Dist: numpy<2; extra == "pymongo"
Requires-Dist: pandas<2.2; extra == "pymongo"
Requires-Dist: pymongo<4.9; extra == "pymongo"
Requires-Dist: sqlalchemy<2; extra == "pymongo"
Provides-Extra: release
Requires-Dist: build<2; extra == "release"
Requires-Dist: twine<7; extra == "release"
Provides-Extra: release-cfr
Requires-Dist: poethepoet<1; extra == "release-cfr"
Requires-Dist: pyinstaller<7; extra == "release-cfr"
Provides-Extra: service
Requires-Dist: fastapi<0.117; extra == "service"
Requires-Dist: uvicorn<0.36; extra == "service"
Provides-Extra: settings
Requires-Dist: cratedb-toolkit[docs-api]; extra == "settings"
Provides-Extra: test
Requires-Dist: cratedb-toolkit[testing]; extra == "test"
Requires-Dist: httpx<0.29; extra == "test"
Requires-Dist: ipywidgets<9; extra == "test"
Requires-Dist: markdown-it-py<4; extra == "test"
Requires-Dist: pueblo[dataframe,notebook,testing]>=0.0.11; extra == "test"
Requires-Dist: pydantic-core<3; extra == "test"
Requires-Dist: responses<0.26; extra == "test"
Requires-Dist: testcontainers[azurite,localstack,minio,postgres]; extra == "test"
Requires-Dist: types-docutils<0.21.0.20250708,>=0.20.0.20240106; extra == "test"
Provides-Extra: test-mongodb
Requires-Dist: cratedb-toolkit[test]; extra == "test-mongodb"
Requires-Dist: testcontainers[mongodb]; extra == "test-mongodb"
Provides-Extra: testing
Requires-Dist: pytest<9; extra == "testing"
Requires-Dist: pytest-cov<7; extra == "testing"
Requires-Dist: pytest-mock<4; extra == "testing"
Requires-Dist: testcontainers<4.13; extra == "testing"
Dynamic: license-file
